Workbook

Sheet Parametros
A1: Parámetros y registro de supuestos – Caso 2: Terremoto en Colombia (10-ago-2026)
A2: Leyenda: texto azul = valor de entrada editable · fondo amarillo = supuesto provisional clave (sensibilidad pendiente) · Tipo: Real (dato de fuente o del enunciado), Calculado, Supuesto.
A4: ID | B4: Parámetro | C4: Valor | D4: Unidad | E4: Tipo | F4: Fuente / justificación
A5: P01 | B5: Costo fijo por plaza-mes (c_f) | C5: 200000 | D5: COP/plaza-mes | E5: Supuesto | F5: PROVISIONAL. Supuesto propio: ≈40–55% del apoyo UNGRD por persona (Cronista 02-sep-2026: $787.907–1.050.543 por hogar-mes). Sin fuente colombiana de costo de operación de campamentos.
A6: P02 | B6: Duración de referencia (T) | C6: 3 | D6: meses | E6: Supuesto | F6: Igual al periodo de 3 pagos del apoyo económico UNGRD (Cronista 02-sep-2026).
A7: P03 | B7: Costo variable por persona (v) | C7: 60000 | D7: COP/persona | E7: Supuesto | F7: Kit de alimentación ($29.730) + kit de aseo ($29.730), gama alta, precios minoristas D1 (El Tiempo, 14-ago-2026). No es precio institucional.
A8: P04 | B8: Costo de transporte | C8: 500 | D8: COP/km·persona | E8: Real | F8: Enunciado del caso (costo lineal).
A9: P05 | B9: Factor de escala – Grande | C9: 0.85 | D9: adimensional | E9: Supuesto | F9: Economías de escala en campamentos grandes.
A10: P06 | B10: Factor de escala – Intermedia | C10: 1 | D10: adimensional | E10: Supuesto | F10: Categoría de referencia.
A11: P07 | B11: Factor de escala – Pequeña | C11: 1.15 | D11: adimensional | E11: Supuesto | F11: Deseconomías de escala en campamentos pequeños.
A12: P08 | B12: Capacidad – Grande | C12: 3000 | D12: personas | E12: Real | F12: Enunciado del caso.
A13: P09 | B13: Capacidad – Intermedia | C13: 1000 | D13: personas | E13: Real | F13: Enunciado del caso.
A14: P10 | B14: Capacidad – Pequeña | C14: 500 | D14: personas | E14: Real | F14: Enunciado del caso.
A15: P11 | B15: Corte población Grande (≥) | C15: 200000 | D15: habitantes | E15: Supuesto | F15: Corte propio (decisión 6).
A16: P12 | B16: Corte población Intermedia (≥) | C16: 100000 | D16: habitantes | E16: Supuesto | F16: Sigue el umbral de 100.000 del Sistema de Ciudades del DNP (verificado solo en fuente secundaria).
... A28: P24 | B28: Tamaño de hogar alternativo | C28: 3 | D28: personas/hogar | E28: Supuesto | F28: Sensibilidad; la base usa personas/familias del RUD por municipio (S6).

Sheet Candidatos
A1: Sitios candidatos y costos – 17 candidatos + 1 reserva
A2: Candidatos pequeños (10 de 17): interpretación sujeta a confirmación del profesor. Coordenadas y distancias: PENDIENTES (validación definitiva por carretera con OSRM/OpenStreetMap antes de cerrar la base).
A4: Identif. | B4: Identif. | C4: Identif. | D4: Identif. | E4: Supuesto | F4: Real | G4: Real | H4: Real | I4: Calculado | J4: Calculado | K4: Real | L4: Supuesto | M4: Calculado | N4: Calculado | O4: Supuesto | P4: Calculado
A5: ID | B5: DIVIPOLA | C5: Municipio | D5: Departamento | E5: Rol | F5: Población DANE 2026 | G5: NH (RUD) | H5: Personas registradas (RUD) | I5: % registrado | J5: Categoría | K5: Capacidad K_j | L5: Factor escala | M5: Costo fijo por plaza (T meses) | N5: Costo fijo f_j | O5: Costo variable v_j | P5: Filtros S2/S7
A6: C01 | B6: 76520 | C6: Palmira | D6: Valle del Cauca | E6: Candidato | F6: 382703 | G6: 74 | H6: 2411 | I6: =H6/F6 -> 0.0062999245 | J6: =IF(F6>=Parametros!$C$15,"Grande",IF(F6>=Parametros!$C$16,"Intermedia","Pequeña")) -> Grande | K6: =IF(J6="Grande",Parametros!$C$12,IF(J6="Intermedia",Parametros!$C$13,Parametros!$C$14)) -> 3000 | L6: =IF(J6="Grande",Parametros!$C$9,IF(J6="Intermedia",Parametros!$C$10,Parametros!$C$11)) -> 0.85 | M6: =Parametros!$C$5*Parametros!$C$6*L6 -> 510000 | N6: =K6*M6 -> 1530000000 | O6: =Parametros!$C$7 -> 60000 | P6: =IF(AND(G6<Parametros!$C$17,I6<Parametros!$C$18),"Cumple","No cumple") -> Cumple
A7: C02 | B7: 76834 | C7: Tuluá | D7: Valle del Cauca | E7: Candidato | F7: 225868 | G7: 66 | H7: 2582 | I7: =H7/F7 -> 0.011431456 | J7: =IF(F7>=Parametros!$C$15,"Grande",IF(F7>=Parametros!$C$16,"Intermedia","Pequeña")) -> Grande | K7: =IF(J7="Grande",Parametros!$C$12,IF(J7="Intermedia",Parametros!$C$13,Parametros!$C$14)) -> 3000 | L7: =IF(J7="Grande",Parametros!$C$9,IF(J7="Intermedia",Parametros!$C$10,Parametros!$C$11)) -> 0.85 | M7: =Parametros!$C$5*Parametros!$C$6*L7 -> 510000 | N7: =K7*M7 -> 1530000000 | O7: =Parametros!$C$7 -> 60000 | P7: =IF(AND(G7<Parametros!$C$17,I7<Parametros!$C$18),"Cumple","No cumple") -> Cumple
A8: C03 | B8: 76364 | C8: Jamundí | D8: Valle del Cauca | E8: Candidato | F8: 196875 | G8: 161 | H8: 4396 | I8: =H8/F8 -> 0.022328889 | J8: =IF(F8>=Parametros!$C$15,"Grande",IF(F8>=Parametros!$C$16,"Intermedia","Pequeña")) -> Intermedia | K8: =IF(J8="Grande",Parametros!$C$12,IF(J8="Intermedia",Parametros!$C$13,Parametros!$C$14)) -> 1000 | L8: =IF(J8="Grande",Parametros!$C$9,IF(J8="Intermedia",Parametros!$C$10,Parametros!$C$11)) -> 1 | M8: =Parametros!$C$5*Parametros!$C$6*L8 -> 600000 | N8: =K8*M8 -> 600000000 | O8: =Parametros!$C$7 -> 60000 | P8: =IF(AND(G8<Parametros!$C$17,I8<Parametros!$C$18),"Cumple","No cumple") -> Cumple
A9: C04 | B9: 76147 | C9: Cartago | D9: Valle del Cauca | E9: Candidato | F9: 144206 | G9: 207 | H9: 2490 | I9: =H9/F9 -> 0.017266965 | J9: =IF(F9>=Parametros!$C$15,"Grande",IF(F9>=Parametros!$C$16,"Intermedia","Pequeña")) -> Intermedia | K9: =IF(J9="Grande",Parametros!$C$12,IF(J9="Intermedia",Parametros!$C$13,Parametros!$C$14)) -> 1000 | L9: =IF(J9="Grande",Parametros!$C$9,IF(J9="Intermedia",Parametros!$C$10,Parametros!$C$11)) -> 1 | M9: =Parametros!$C$5*Parametros!$C$6*L9 -> 600000 | N9: =K9*M9 -> 600000000 | O9: =Parametros!$C$7 -> 60000 | P9: =IF(AND(G9<Parametros!$C$17,I9<Parametros!$C$18),"Cumple","No cumple") -> Cumple
A10: C05 | B10: 76111 | C10: Guadalajara de Buga | D10: Valle del Cauca | E10: Candidato | F10: 132250 | G10: 80 | H10: 1554 | I10: =H10/F10 -> 0.011750473 | J10: =IF(F10>=Parametros!$C$15,"Grande",IF(F10>=Parametros!$C$16,"Intermedia","Pequeña")) -> Intermedia | K10: =IF(J10="Grande",Parametros!$C$12,IF(J10="Intermedia",Parametros!$C$13,Parametros!$C$14)) -> 1000 | L10: =IF(J10="Grande",Parametros!$C$9,IF(J10="Intermedia",Parametros!$C$10,Parametros!$C$11)) -> 1 | M10: =Parametros!$C$5*Parametros!$C$6*L10 -> 600000 | N10: =K10*M10 -> 600000000 | O10: =Parametros!$C$7 -> 60000 | P10: =IF(AND(G10<Parametros!$C$17,I10<Parametros!$C$18),"Cumple","No cumple") -> Cumple
A11: C06 | B11: 76130 | C11: Candelaria | D11: Valle del Cauca | E11: Candidato | F11: 115933 | G11: 22 | H11: 573 | I11: =H11/F11 -> 0.0049425099 | J11: =IF(F11>=Parametros!$C$15,"Grande",IF(F11>=Parametros!$C$16,"Intermedia","Pequeña")) -> Intermedia | K11: =IF(J11="Grande",Parametros!$C$12,IF(J11="Intermedia",Parametros!$C$13,Parametros!$C$14)) -> 1000 | L11: =IF(J11="Grande",Parametros!$C$9,IF(J11="Intermedia",Parametros!$C$10,Parametros!$C$11)) -> 1 | M11: =Parametros!$C$5*Parametros!$C$6*L11 -> 600000 | N11: =K11*M11 -> 600000000 | O11: =Parametros!$C$7 -> 60000 | P11: =IF(AND(G11<Parametros!$C$17,I11<Parametros!$C$18),"Cumple","No cumple") -> Cumple
A12: C07 | B12: 76892 | C12: Yumbo | D12: Valle del Cauca | E12: Candidato | F12: 115667 | G12: 158 | H12: 2388 | I12: =H12/F12 -> 0.020645474 | J12: =IF(F12>=Parametros!$C$15,"Grande",IF(F12>=Parametros!$C$16,"Intermedia","Pequeña")) -> Intermedia | K12: =IF(J12="Grande",Parametros!$C$12,IF(J12="Intermedia",Parametros!$C$13,Parametros!$C$14)) -> 1000 | L12: =IF(J12="Grande",Parametros!$C$9,IF(J12="Intermedia",Parametros!$C$10,Parametros!$C$11)) -> 1 | M12: =Parametros!$C$5*Parametros!$C$6*L12 -> 600000 | N12: =K12*M12 -> 600000000 | O12: =Parametros!$C$7 -> 60000 | P12: =IF(AND(G12<Parametros!$C$17,I12<Parametros!$C$18),"Cumple","No cumple") -> Cumple
A13: C08 | B13: 76275 | C13: Florida | D13: Valle del Cauca | E13: Candidato | F13: 57017 | G13: 19 | H13: 986 | I13: =H13/F13 -> 0.017293088 | J13: =IF(F13>=Parametros!$C$15,"Grande",IF(F13>=Parametros!$C$16,"Intermedia","Pequeña")) -> Pequeña | K13: =IF(J13="Grande",Parametros!$C$12,IF(J13="Intermedia",Parametros!$C$13,Parametros!$C$14)) -> 500 | L13: =IF(J13="Grande",Parametros!$C$9,IF(J13="Intermedia",Parametros!$C$10,Parametros!$C$11)) -> 1.15 | M13: =Parametros!$C$5*Parametros!$C$6*L13 -> 690000 | N13: =K13*M13 -> 345000000 | O13: =Parametros!$C$7 -> 60000 | P13: =IF(AND(G13<Parametros!$C$17,I13<Parametros!$C$18),"Cumple","No cumple") -> Cumple
A14: C09 | B14: 76248 | C14: El Cerrito | D14: Valle del Cauca | E14: Candidato | F14: 56397 | G14: 21 | H14: 537 | I14: =H14/F14 -> 0.0095217831 | J14: =IF(F14>=Parametros!$C$15,"Grande",IF(F14>=Parametros!$C$16,"Intermedia","Pequeña")) -> Pequeña | K14: =IF(J14="Grande",Parametros!$C$12,IF(J14="Intermedia",Parametros!$C$13,Parametros!$C$14)) -> 500 | L14: =IF(J14="Grande",Parametros!$C$9,IF(J14="Intermedia",Parametros!$C$10,Parametros!$C$11)) -> 1.15 | M14: =Parametros!$C$5*Parametros!$C$6*L14 -> 690000 | N14: =K14*M14 -> 345000000 | O14: =Parametros!$C$7 -> 60000 | P14: =IF(AND(G14<Parametros!$C$17,I14<Parametros!$C$18),"Cumple","No cumple") -> Cumple
A15: C10 | B15: 76563 | C15: Pradera | D15: Valle del Cauca | E15: Candidato | F15: 50067 | G15: 16 | H15: 742 | I15: =H15/F15 -> 0.014820141 | J15: =IF(F15>=Parametros!$C$15,"Grande",IF(F15>=Parametros!$C$16,"Intermedia","Pequeña")) -> Pequeña | K15: =IF(J15="Grande",Parametros!$C$12,IF(J15="Intermedia",Parametros!$C$13,Parametros!$C$14)) -> 500 | L15: =IF(J15="Grande",Parametros!$C$9,IF(J15="Intermedia",Parametros!$C$10,Parametros!$C$11)) -> 1.15 | M15: =Parametros!$C$5*Parametros!$C$6*L15 -> 690000 | N15: =K15*M15 -> 345000000 | O15: =Parametros!$C$7 -> 60000 | P15: =IF(AND(G15<Parametros!$C$17,I15<Parametros!$C$18),"Cumple","No cumple") -> Cumple
A16: C11 | B16: 76318 | C16: Guacarí | D16: Valle del Cauca | E16: Candidato | F16: 34739 | G16: 47 | H16: 373 | I16: =H16/F16 -> 0.010737212 | J16: =IF(F16>=Parametros!$C$15,"Grande",IF(F16>=Parametros!$C$16,"Intermedia","Pequeña")) -> Pequeña | K16: =IF(J16="Grande",Parametros!$C$12,IF(J16="Intermedia",Parametros!$C$13,Parametros!$C$14)) -> 500 | L16: =IF(J16="Grande",Parametros!$C$9,IF(J16="Intermedia",Parametros!$C$10,Parametros!$C$11)) -> 1.15 | M16: =Parametros!$C$5*Parametros!$C$6*L16 -> 690000 | N16: =K16*M16 -> 345000000 | O16: =Parametros!$C$7 -> 60000 | P16: =IF(AND(G16<Parametros!$C$17,I16<Parametros!$C$18),"Cumple","No cumple") -> Cumple
A17: C12 | B17: 76306 | C17: Ginebra | D17: Valle del Cauca | E17: Candidato | F17: 24545 | G17: 14 | H17: 740 | I17: =H17/F17 -> 0.030148706 | J17: =IF(F17>=Parametros!$C$15,"Grande",IF(F17>=Parametros!$C$16,"Intermedia","Pequeña")) -> Pequeña | K17: =IF(J17="Grande",Parametros!$C$12,IF(J17="Intermedia",Parametros!$C$13,Parametros!$C$14)) -> 500 | L17: =IF(J17="Grande",Parametros!$C$9,IF(J17="Intermedia",Parametros!$C$10,Parametros!$C$11)) -> 1.15 | M17: =Parametros!$C$5*Parametros!$C$6*L17 -> 690000 | N17: =K17*M17 -> 345000000 | O17: =Parametros!$C$7 -> 60000 | P17: =IF(AND(G17<Parametros!$C$17,I17<Parametros!$C$18),"Cumple","No cumple") -> Cumple
... A22: C17 | B22: 17380 | C22: La Dorada | D22: Caldas | E22: Candidato | F22: 71480 | G22: 3 | H22: 147 | I22: =H22/F22 -> 0.0020565193 | J22: =IF(F22>=Parametros!$C$15,"Grande",IF(F22>=Parametros!$C$16,"Intermedia","Pequeña")) -> Pequeña | K22: =IF(J22="Grande",Parametros!$C$12,IF(J22="Intermedia",Parametros!$C$13,Parametros!$C$14)) -> 500 | L22: =IF(J22="Grande",Parametros!$C$9,IF(J22="Intermedia",Parametros!$C$10,Parametros!$C$11)) -> 1.15 | M22: =Parametros!$C$5*Parametros!$C$6*L22 -> 690000 | N22: =K22*M22 -> 345000000 | O22: =Parametros!$C$7 -> 60000 | P22: =IF(AND(G22<Parametros!$C$17,I22<Parametros!$C$18),"Cumple","No cumple") -> Cumple
A24: Reserva (no entra al cálculo del presupuesto ni a los 17 candidatos base):
A25: R01 | B25: 63401 | C25: La Tebaida | D25: Quindío | E25: Reserva | F25: 33758 | G25: 95 | H25: 2773 | I25: =H25/F25 -> 0.082143492 | J25: =IF(F25>=Parametros!$C$15,"Grande",IF(F25>=Parametros!$C$16,"Intermedia","Pequeña")) -> Pequeña | K25: =IF(J25="Grande",Parametros!$C$12,IF(J25="Intermedia",Parametros!$C$13,Parametros!$C$14)) -> 500 | L25: =IF(J25="Grande",Parametros!$C$9,IF(J25="Intermedia",Parametros!$C$10,Parametros!$C$11)) -> 1.15 | M25: =Parametros!$C$5*Parametros!$C$6*L25 -> 690000 | N25: =K25*M25 -> 345000000 | O25: =Parametros!$C$7 -> 60000 | P25: =IF(AND(G25<Parametros!$C$17,I25<Parametros!$C$18),"Cumple","No cumple") -> No cumple
A27: Notas: (1) NH y personas registradas provienen del consolidado del RUD (corte 17-sep-2026), agregador secundario datosdelterremoto.org. (2) Población: DANE, Proyecciones municipales 2018-2042. (3) La Tebaida no cumple el filtro S7 (8,2%); se mantiene como reserva por su cercanía a Armenia.

Sheet Presupuesto
A1: Presupuesto y escenarios (COP)
A3: Σ costo fijo de los 10 campamentos candidatos más grandes | B3: =SUMPRODUCT(LARGE(Candidatos!$N$6:$N$22,{1,2,3,4,5,6,7,8,9,10})) -> 7095000000 | C3: Calculado
A4: % del enunciado | B4: =Parametros!$C$21 -> 0.5 | C4: Real
A5: Presupuesto BASE | B5: =B3*B4 -> 3547500000 | C5: Calculado
A6: Presupuesto escenario A (reducción P18) | B6: =B5*(1-Parametros!$C$22) -> 3015375000 | C6: Calculado
A7: Presupuesto escenario B (reducción P19) | B7: =B5*(1-Parametros!$C$23) -> 2483250000 | C7: Calculado
A8: Σ costo fijo de los 17 candidatos (abrir todos) | B8: =SUM(Candidatos!$N$6:$N$22) -> 9510000000 | C8: Calculado
A9: Capacidad total de los 17 candidatos (personas) | B9: =SUM(Candidatos!$K$6:$K$22) -> 16000 | C9: Calculado
A10: Presupuesto base / costo de abrir todos | B10: =B5/B8 -> 0.37302839 | C10: Calculado
A13: Sensibilidad del costo fijo por plaza-mes (c_f). Los costos fijos y el presupuesto escalan linealmente con c_f.
A14: c_f (COP/plaza-mes) | B14: Costo fijo Grande | C14: Costo fijo Intermedia | D14: Costo fijo Pequeña | E14: Presupuesto BASE | F14: Presupuesto A | G14: Presupuesto B
A15: 100000 | B15: =Parametros!$C$12*A15*Parametros!$C$6*Parametros!$C$9 -> 765000000 | C15: =Parametros!$C$13*A15*Parametros!$C$6*Parametros!$C$10 -> 300000000 | D15: =Parametros!$C$14*A15*Parametros!$C$6*Parametros!$C$11 -> 172500000 | E15: =$B$5*A15/Parametros!$C$5 -> 1773750000 | F15: =E15*(1-Parametros!$C$22) -> 1507687500 | G15: =E15*(1-Parametros!$C$23) -> 1241625000
A16: 150000 | B16: =Parametros!$C$12*A16*Parametros!$C$6*Parametros!$C$9 -> 1147500000 | C16: =Parametros!$C$13*A16*Parametros!$C$6*Parametros!$C$10 -> 450000000 | D16: =Parametros!$C$14*A16*Parametros!$C$6*Parametros!$C$11 -> 258750000 | E16: =$B$5*A16/Parametros!$C$5 -> 2660625000 | F16: =E16*(1-Parametros!$C$22) -> 2261531250 | G16: =E16*(1-Parametros!$C$23) -> 1862437500
A17: 200000 | B17: =Parametros!$C$12*A17*Parametros!$C$6*Parametros!$C$9 -> 1530000000 | C17: =Parametros!$C$13*A17*Parametros!$C$6*Parametros!$C$10 -> 600000000 | D17: =Parametros!$C$14*A17*Parametros!$C$6*Parametros!$C$11 -> 345000000 | E17: =$B$5*A17/Parametros!$C$5 -> 3547500000 | F17: =E17*(1-Parametros!$C$22) -> 3015375000 | G17: =E17*(1-Parametros!$C$23) -> 2483250000
A18: 250000 | B18: =Parametros!$C$12*A18*Parametros!$C$6*Parametros!$C$9 -> 1912500000 | C18: =Parametros!$C$13*A18*Parametros!$C$6*Parametros!$C$10 -> 750000000 | D18: =Parametros!$C$14*A18*Parametros!$C$6*Parametros!$C$11 -> 431250000 | E18: =$B$5*A18/Parametros!$C$5 -> 4434375000 | F18: =E18*(1-Parametros!$C$22) -> 3769218750 | G18: =E18*(1-Parametros!$C$23) -> 3104062500
A19: 300000 | B19: =Parametros!$C$12*A19*Parametros!$C$6*Parametros!$C$9 -> 2295000000 | C19: =Parametros!$C$13*A19*Parametros!$C$6*Parametros!$C$10 -> 900000000 | D19: =Parametros!$C$14*A19*Parametros!$C$6*Parametros!$C$11 -> 517500000 | E19: =$B$5*A19/Parametros!$C$5 -> 5321250000 | F19: =E19*(1-Parametros!$C$22) -> 4523062500 | G19: =E19*(1-Parametros!$C$23) -> 3724875000
A20: 400000 | B20: =Parametros!$C$12*A20*Parametros!$C$6*Parametros!$C$9 -> 3060000000 | C20: =Parametros!$C$13*A20*Parametros!$C$6*Parametros!$C$10 -> 1200000000 | D20: =Parametros!$C$14*A20*Parametros!$C$6*Parametros!$C$11 -> 690000000 | E20: =$B$5*A20/Parametros!$C$5 -> 7095000000 | F20: =E20*(1-Parametros!$C$22) -> 6030750000 | G20: =E20*(1-Parametros!$C$23) -> 4966500000
A22: Nota: la fila con c_f = P01 reproduce el presupuesto base. El escalamiento lineal del presupuesto es válido porque todo costo fijo es proporcional a c_f.

Sheet Demanda
A1: Puntos de demanda – 29 municipios (NH ≥ 400, corte RUD 17-sep-2026)
A3: Identif. | B3: Identif. | C3: Identif. | D3: Real | E3: Real | F3: Real | G3: Real | H3: Calculado | I3: Calculado | J3: Calculado | K3: Calculado | L3: Calculado | M3: Calculado | N3: Calculado | O3: Calculado | P3: Real
A4: DIVIPOLA | B4: Municipio | C4: Departamento | D4: Población DANE 2026 | E4: NH (RUD) | F4: Familias (RUD) | G4: Personas registradas (RUD) | H4: Hogar RUD (pers/fam) | I4: Personas en NH | J4: d_i f=2% | K4: d_i f=5% | L4: d_i f=10% (BASE) | M4: d_i f=13% | N4: d_i f=10% hogar 3,0 | O4: % registrado | P4: Calidad dato RUD
A5: 66001 | B5: Pereira | C5: Risaralda | D5: 487820 | E5: 23873 | F5: 47211 | G5: 110882 | H5: =G5/F5 -> 2.3486476 | I5: =E5*H5 -> 56069.263 | J5: =ROUND(I5*Parametros!$C$25,0) -> 1121 | K5: =ROUND(I5*Parametros!$C$26,0) -> 2803 | L5: =ROUND(I5*Parametros!$C$24,0) -> 5607 | M5: =ROUND(I5*Parametros!$C$27,0) -> 7289 | N5: =ROUND(E5*Parametros!$C$28*Parametros!$C$24,0) -> 7162 | O5: =G5/D5 -> 0.22730105 | P5: F
A6: 76001 | B6: Cali | C6: Valle del Cauca | D6: 2269983 | E6: 21309 | F6: 45138 | G6: 97337 | H6: =G6/F6 -> 2.1564314 | I6: =E6*H6 -> 45951.396 | J6: =ROUND(I6*Parametros!$C$25,0) -> 919 | K6: =ROUND(I6*Parametros!$C$26,0) -> 2298 | L6: =ROUND(I6*Parametros!$C$24,0) -> 4595 | M6: =ROUND(I6*Parametros!$C$27,0) -> 5974 | N6: =ROUND(E6*Parametros!$C$28*Parametros!$C$24,0) -> 6393 | O6: =G6/D6 -> 0.042880057 | P6: F
A7: 76109 | B7: Buenaventura | C7: Valle del Cauca | D7: 335217 | E7: 9557 | F7: 31654 | G7: 67590 | H7: =G7/F7 -> 2.1352752 | I7: =E7*H7 -> 20406.825 | J7: =ROUND(I7*Parametros!$C$25,0) -> 408 | K7: =ROUND(I7*Parametros!$C$26,0) -> 1020 | L7: =ROUND(I7*Parametros!$C$24,0) -> 2041 | M7: =ROUND(I7*Parametros!$C$27,0) -> 2653 | N7: =ROUND(E7*Parametros!$C$28*Parametros!$C$24,0) -> 2867 | O7: =G7/D7 -> 0.20163059 | P7: F
A8: 63001 | B8: Armenia | C8: Quindío | D8: 307103 | E8: 7270 | F8: 21935 | G8: 41197 | H8: =G8/F8 -> 1.87814 | I8: =E8*H8 -> 13654.078 | J8: =ROUND(I8*Parametros!$C$25,0) -> 273 | K8: =ROUND(I8*Parametros!$C$26,0) -> 683 | L8: =ROUND(I8*Parametros!$C$24,0) -> 1365 | M8: =ROUND(I8*Parametros!$C$27,0) -> 1775 | N8: =ROUND(E8*Parametros!$C$28*Parametros!$C$24,0) -> 2181 | O8: =G8/D8 -> 0.13414718 | P8: F
A9: 66170 | B9: Dosquebradas | C9: Risaralda | D9: 246388 | E9: 4179 | F9: 8116 | G9: 17742 | H9: =G9/F9 -> 2.1860522 | I9: =E9*H9 -> 9135.5123 | J9: =ROUND(I9*Parametros!$C$25,0) -> 183 | K9: =ROUND(I9*Parametros!$C$26,0) -> 457 | L9: =ROUND(I9*Parametros!$C$24,0) -> 914 | M9: =ROUND(I9*Parametros!$C$27,0) -> 1188 | N9: =ROUND(E9*Parametros!$C$28*Parametros!$C$24,0) -> 1254 | O9: =G9/D9 -> 0.072008377 | P9: F
A10: 17001 | B10: Manizales | C10: Caldas | D10: 475690 | E10: 4590 | F10: 9125 | G10: 14359 | H10: =G10/F10 -> 1.573589 | I10: =E10*H10 -> 7222.7737 | J10: =ROUND(I10*Parametros!$C$25,0) -> 144 | K10: =ROUND(I10*Parametros!$C$26,0) -> 361 | L10: =ROUND(I10*Parametros!$C$24,0) -> 722 | M10: =ROUND(I10*Parametros!$C$27,0) -> 939 | N10: =ROUND(E10*Parametros!$C$28*Parametros!$C$24,0) -> 1377 | O10: =G10/D10 -> 0.030185625 | P10: F
A11: 66682 | B11: Santa Rosa de Cabal | C11: Risaralda | D11: 84054 | E11: 1904 | F11: 5202 | G11: 11899 | H11: =G11/F11 -> 2.2873895 | I11: =E11*H11 -> 4355.1895 | J11: =ROUND(I11*Parametros!$C$25,0) -> 87 | K11: =ROUND(I11*Parametros!$C$26,0) -> 218 | L11: =ROUND(I11*Parametros!$C$24,0) -> 436 | M11: =ROUND(I11*Parametros!$C$27,0) -> 566 | N11: =ROUND(E11*Parametros!$C$28*Parametros!$C$24,0) -> 571 | O11: =G11/D11 -> 0.14156376 | P11: R
A12: 63594 | B12: Quimbaya | C12: Quindío | D12: 31350 | E12: 1683 | F12: 5728 | G12: 12739 | H12: =G12/F12 -> 2.2239874 | I12: =E12*H12 -> 3742.9708 | J12: =ROUND(I12*Parametros!$C$25,0) -> 75 | K12: =ROUND(I12*Parametros!$C$26,0) -> 187 | L12: =ROUND(I12*Parametros!$C$24,0) -> 374 | M12: =ROUND(I12*Parametros!$C$27,0) -> 487 | N12: =ROUND(E12*Parametros!$C$28*Parametros!$C$24,0) -> 505 | O12: =G12/D12 -> 0.40634769 | P12: F
A13: 76233 | B13: Dagua | C13: Valle del Cauca | D13: 60038 | E13: 1635 | F13: 5272 | G13: 11355 | H13: =G13/F13 -> 2.1538316 | I13: =E13*H13 -> 3521.5146 | J13: =ROUND(I13*Parametros!$C$25,0) -> 70 | K13: =ROUND(I13*Parametros!$C$26,0) -> 176 | L13: =ROUND(I13*Parametros!$C$24,0) -> 352 | M13: =ROUND(I13*Parametros!$C$27,0) -> 458 | N13: =ROUND(E13*Parametros!$C$28*Parametros!$C$24,0) -> 491 | O13: =G13/D13 -> 0.18913022 | P13: P
A14: 63470 | B14: Montenegro | C14: Quindío | D14: 37483 | E14: 1048 | F14: 5423 | G14: 12407 | H14: =G14/F14 -> 2.2878481 | I14: =E14*H14 -> 2397.6648 | J14: =ROUND(I14*Parametros!$C$25,0) -> 48 | K14: =ROUND(I14*Parametros!$C$26,0) -> 120 | L14: =ROUND(I14*Parametros!$C$24,0) -> 240 | M14: =ROUND(I14*Parametros!$C$27,0) -> 312 | N14: =ROUND(E14*Parametros!$C$28*Parametros!$C$24,0) -> 314 | O14: =G14/D14 -> 0.33100339 | P14: F
A15: 76622 | B15: Roldanillo | C15: Valle del Cauca | D15: 38639 | E15: 1519 | F15: 6146 | G15: 9296 | H15: =G15/F15 -> 1.5125285 | I15: =E15*H15 -> 2297.5308 | J15: =ROUND(I15*Parametros!$C$25,0) -> 46 | K15: =ROUND(I15*Parametros!$C$26,0) -> 115 | L15: =ROUND(I15*Parametros!$C$24,0) -> 230 | M15: =ROUND(I15*Parametros!$C$27,0) -> 299 | N15: =ROUND(E15*Parametros!$C$28*Parametros!$C$24,0) -> 456 | O15: =G15/D15 -> 0.24058594 | P15: F
A16: 76890 | B16: Yotoco | C16: Valle del Cauca | D16: 16843 | E16: 651 | F16: 2522 | G16: 6237 | H16: =G16/F16 -> 2.4730373 | I16: =E16*H16 -> 1609.9473 | J16: =ROUND(I16*Parametros!$C$25,0) -> 32 | K16: =ROUND(I16*Parametros!$C$26,0) -> 80 | L16: =ROUND(I16*Parametros!$C$24,0) -> 161 | M16: =ROUND(I16*Parametros!$C$27,0) -> 209 | N16: =ROUND(E16*Parametros!$C$28*Parametros!$C$24,0) -> 195 | O16: =G16/D16 -> 0.3703022 | P16: F
... A33: 63130 | B33: Calarcá | C33: Quindío | D33: 74399 | E33: 450 | F33: 6883 | G33: 10370 | H33: =G33/F33 -> 1.5066105 | I33: =E33*H33 -> 677.97472 | J33: =ROUND(I33*Parametros!$C$25,0) -> 14 | K33: =ROUND(I33*Parametros!$C$26,0) -> 34 | L33: =ROUND(I33*Parametros!$C$24,0) -> 68 | M33: =ROUND(I33*Parametros!$C$27,0) -> 88 | N33: =ROUND(E33*Parametros!$C$28*Parametros!$C$24,0) -> 135 | O33: =G33/D33 -> 0.13938359 | P33: F
B34: TOTAL | E34: =SUM(E5:E33) -> 88091 | I34: =SUM(I5:I33) -> 188790.19 | J34: =SUM(J5:J33) -> 3777 | K34: =SUM(K5:K33) -> 9438 | L34: =SUM(L5:L33) -> 18880 | M34: =SUM(M5:M33) -> 24546 | N34: =SUM(N5:N33) -> 26428
A36: Calidad del dato: F = fuerte (RUD y reporte territorial), P = parcial, R = solo RUD. Hogar RUD = personas registradas / familias registradas (puede subestimar el tamaño real).
